fractal_lif_converters/__FRACTAL_MANIFEST__.json
fractal_lif_converters/__init__.py
fractal_lif_converters/convert_lif_compute_task.py
fractal_lif_converters/convert_lif_plate_init_task.py
fractal_lif_converters/convert_lif_scene_init_task.py
fractal_lif_converters/wrappers.py
fractal_lif_converters/dev/create_manifest.py
fractal_lif_converters/dev/task_list.py
fractal_lif_converters/utils/__init__.py
fractal_lif_converters/utils/_errors.py
fractal_lif_converters/utils/converter_utils.py
fractal_lif_converters/utils/lif_utils.py
fractal_lif_converters/utils/ngff_image_meta_utils.py
fractal_lif_converters/utils/ngff_plate_meta_utils.py
fractal_lif_converters-3.0.3.dist-info/METADATA
fractal_lif_converters-3.0.3.dist-info/WHEEL
fractal_lif_converters-3.0.3.dist-info/licenses/LICENSE
fractal_lif_converters-3.0.3.dist-info/RECORD
