Metadata-Version: 2.3
Name: fractal-lif-converters
Version: 3.0.3
Summary: Package description.
Author-email: Lorenzo Cerrone <lorenzo.cerrone@uzh.ch>
License: GPL-3.0
License-File: LICENSE
Requires-Python: >=3.10
Requires-Dist: bioio
Requires-Dist: bioio-lif
Requires-Dist: fractal-tasks-core==1.3.1
Requires-Dist: ngio==0.1.0beta3
Requires-Dist: numpy
Provides-Extra: dev
Requires-Dist: devtools; extra == 'dev'
Requires-Dist: hatch; extra == 'dev'
Requires-Dist: jsonschema; extra == 'dev'
Requires-Dist: pre-commit; extra == 'dev'
Requires-Dist: pytest; extra == 'dev'
Requires-Dist: pytest-cov; extra == 'dev'
Requires-Dist: requests; extra == 'dev'
Requires-Dist: ruff; extra == 'dev'
